{
  "info": {
    "id": 38009486,
    "dataType": "판결문",
    "caseNm": "임금",
    "caseTitle": "수원지방법원 2002. 1. 10. 선고 2001가합5541 판결：항소기각, 상고",
    "courtType": "판례(하급심)",
    "courtNm": "수원지방법원",
    "judmnAdjuDe": "2002-01-10",
    "caseNoID": "2001가합5541",
    "caseNo": "2001가합5541"
  },
  "jdgmn": "공무원에서 공사 직원 또는 주식회사 직원으로 신분 전환된 자들에 대하여 법률상 보장된 정년 보장의 권리가 노동조합의 동의에 의해 제한될 수 있는지 여부(소극)",
  "jdgmnInfo": [
    {
      "question": "공무원에서 공사 직원 또는 주식회사 직원으로 신분 전환된 자들에 대하여 법률상 보장된 정년 보장의 권리가 노동조합의 동의에 의해 제한될 수 있는가?",
      "answer": "부정"
    }
  ],
  "Summary": [
    {
      "summ_contxt": "법률에 의하여 부여된 정년 보장의 권리가 그와 같은 권리와 전혀 무관한 다수의 근로자가 구성원인 노동조합에서 다수결에 의한 동의로써 박탈된다고 보는 것은 부당하므로, 한국전기통신공사가 인사규정을 개정하면서 노동조합의 동의를 얻었을 뿐 이해당사자들로부터 동의를 얻은 바 없는 경우, 그 개정 인사규정은 당사자들에 대하여는 효력이 없다.",
      "summ_pass": "한국전기통신공사가 인사규정을 개정하면서 노동조합의 동의를 얻었을 뿐 이해당사자들로부터 동의를 얻은 바 없는 경우, 그 개정 인사규정은 당사자들에 대하여는 효력이 없다."
    }
  ],
  "keyword_tagg": [
    {
      "id": 1,
      "keyword": "정년 보장의 권리"
    }
  ],
  "Reference_info": {
    "reference_rules": "구 한국전기통신공사법(1997. 10. 1. 법률 제5387호에 의해 폐지되기 전의 것) 부칙(1986. 5. 12.) 제3항, 한국전기통신공사법폐지법률(1997. 8. 28. 법률 제5387호) 부칙 제6조",
    "reference_court_case": ""
  },
  "Class_info": {
    "class_name": "근로자",
    "instance_name": "임금"
  }
}