{
  "info": {
    "id": 56569581,
    "dataType": "판결문",
    "caseNm": "직장보육시설지원금지급거부처분취소청구",
    "caseTitle": "국민권익위원회 2001-03194, 2001. 5. 14.",
    "courtType": "심결례",
    "courtNm": "국민권익위원회",
    "judmnAdjuDe": "2001-05-14",
    "caseNoID": "2001-03194",
    "caseNo": "2001-03194"
  },
  "jdgmn": "",
  "jdgmnInfo": [
    {
      "question": "피청구인의 지원금지급기준에 해당하지 아니함이 분명하므로, 위 지원금지급기준에 따른 피청구인의 직장보육시설지원금지급이 거부됨이 위법·부당한가?",
      "answer": "부정"
    }
  ],
  "Summary": [
    {
      "summ_contxt": "다음, 청구인이 지원금지급대상에 해당하는지의 여부를 살피건대, 청구인의 직장보육시설은 2000년 3/4분기중 등록된 고용보험 피보험 자녀의 비율이 전체 보육아동의 7%에 불과하여 피청구인의 지원금지급기준에 해당하지 아니함이 분명하므로, 위 지원금지급기준에 따른 피청구인의 이 건 처분이 위법·부당하다고 할 수 없을 것이다.",
      "summ_pass": "피청구인의 지원금지급기준에 해당하지 아니함이 분명하므로, 위 지원금지급기준에 따른 피청구인의 이 건 처분이 위법·부당하다고 할 수 없을 것이다."
    }
  ],
  "keyword_tagg": [
    {
      "id": 1,
      "keyword": "직장보육시설지원금"
    }
  ],
  "Reference_info": {
    "reference_rules": "",
    "reference_court_case": ""
  },
  "Class_info": {
    "class_name": "근로자",
    "instance_name": "직장보육시설지원금"
  }
}