{
  "info": {
    "id": 42009730,
    "dataType": "판결문",
    "caseNm": "임금등",
    "caseTitle": "대법원 2004. 5. 14. 선고 2002다23185 판결",
    "courtType": "판례(대법원)",
    "courtNm": "대법원",
    "judmnAdjuDe": "2004-05-14",
    "caseNoID": "2002다23185",
    "caseNo": "2002다23185"
  },
  "jdgmn": "[1] 취업규칙에 규정된 기존의 근로조건을 종전보다 불리하게 변경하기 위한 근로자측의 동의방법 및 근로자 과반수 동의의 소극적 요건인 ‘사용자측의 개입이나 간섭’의 의미\n[2] 근로자의 집단적 의사결정방법에 의한 동의 없이 근로자에게 불리하게 작성·변경된 취업규칙이라도 사회통념상 합리성이 있다고 인정되는 경우에는 그 적용이 가능한지 여부(적극) 및 합리성 유무의 판단 기준\n[3] 복수의 회사가 합병된 경우, 피합병회사와 그 근로자 사이의 집단적인 근로관계나 근로조건 등이 피합병회사의 근로자들과 합병회사 사이에 그대로 승계되는 것인지 여부(적극) 및 합병회사의 노동조합이 유니온 숍의 조직형태라고 하더라도 피합병회사의 근로자들이 자동적으로 합병회사의 노동조합의 조합원으로 되는 것인지 여부(소극)\n[4] 노동조합및노동관계조정법 제35조에 규정된 ‘동종의 근로자’의 의미 및 서로 다른 종류의 사업을 운영하던 회사들이 합병한 이후 그 중 한 사업부문의 근로자들로 구성된 노동조합이 회사와 체결한 단체협약은 다른 사업부문의 근로자들에게도 적용될 수 있는지 여부(소극)",
  "jdgmnInfo": [
    {
      "question": "노동조합및노동관계조정법 제35조에 규정된 ‘동종의 근로자’의 의미 및 서로 다른 종류의 사업을 운영하던 회사들이 합병한 이후 그 중 한 사업부문의 근로자들로 구성된 노동조합이 회사와 체결한 단체협약은 다른 사업부문의 근로자들에게도 적용될 수 있는가?",
      "answer": "부정"
    }
  ],
  "Summary": [
    {
      "summ_contxt": "노동조합및노동관계조정법 제35조는 하나의 사업 또는 사업장에 상시 사용되는 동종의 근로자 반수 이상이 하나의 단체협약의 적용을 받게 된 때에는 당해 사업 또는 사업장에 사용되는 다른 동종의 근로자에 대하여도 당해 단체협약이 적용된다고 규정하고 있는데, 이 규정에 따라 단체협약의 적용을 받게 되는 동종의 근로자라 함은 당해 단체협약의 규정에 의하여 그 협약의 적용이 예상되는 자를 가리키는 것인바, 서로 다른 종류의 사업을 운영하던 회사들이 합병한 이후 근로자들의 근로관계 내용을 단일화하기로 변경·조정하는 새로운 합의가 있기 전에 그 중 한 사업부문의 근로자들로 구성된 노동조합이 회사와 체결한 단체협약은 그 사업부문의 근로자들에 대하여만 적용될 것이 예상되는 것이라 할 것이어서 다른 사업부문의 근로자들에게는 적용될 수 없다.",
      "summ_pass": "서로 다른 종류의 사업을 운영하던 회사들이 합병한 이후 근로자들의 근로관계 내용을 단일화하기로 변경·조정하는 새로운 합의가 있기 전에 그 중 한 사업부문의 근로자들로 구성된 노동조합이 회사와 체결한 단체협약은 그 사업부문의 근로자들에 대하여만 적용될 것이 예상되는 것이라 할 것이어서 다른 사업부문의 근로자들에게는 적용될 수 없다."
    }
  ],
  "keyword_tagg": [
    {
      "id": 1,
      "keyword": "노동조합"
    }
  ],
  "Reference_info": {
    "reference_rules": "[1] 근로기준법 제97조 [2] 근로기준법 제97조 [3] 노동조합및노동관계조정법 제5조, 제31조, 제81조 제2호 [4] 노동조합및노동관계조정법 제35조",
    "reference_court_case": "[1] 대법원 1993. 8. 24. 선고 93다17898 판결(공1993하, 2606), 대법원 1994. 9. 23. 선고 94다23180 판결(공1994하, 2797), 대법원 2003. 11. 14. 선고 2001다18322 판결(공2003하, 2322) [2][4] 대법원 2003. 6. 27. 선고 2002다23611 판결 [2] 대법원 1997. 5. 16. 선고 96다2507 판결(공1997하, 1820), 대법원 2000. 9. 29. 선고 99다45376 판결(공2000하, 2186), 대법원 2001. 1. 5. 선고 99다70846 판결(공2001상, 419) [4] 대법원 1997. 4. 25. 선고 95다4056 판결(공1997상, 1555), 대법원 1997. 10. 28. 선고 96다13415 판결(공1997하, 3620), 대법원 2004. 2. 12. 선고 2001다63599 판결(공2004상, 441)"
  },
  "Class_info": {
    "class_name": "근로자",
    "instance_name": "임금"
  }
}