{
  "info": {
    "id": 38010387,
    "dataType": "판결문",
    "caseNm": "산업재해보상보험료부과처분등취소청구",
    "caseTitle": "국민권익위원회 2003-02349, 2003. 7. 21.",
    "courtType": "심결례",
    "courtNm": "국민권익위원회",
    "judmnAdjuDe": "2003-07-21",
    "caseNoID": "2003-02349",
    "caseNo": "2003-02349"
  },
  "jdgmn": "",
  "jdgmnInfo": [
    {
      "question": "납부의무자의 보험관계 업무상 편의를 위하여 보험료부과내역이 적힌 이 건 납부서를 송부하였다 하더라도 이는 피청구인이 납부의무자로 하여금 자진납부하도록 안내한 것에 불과하다고 보아야 하는가?",
      "answer": "긍정"
    }
  ],
  "Summary": [
    {
      "summ_contxt": "청구인이 2003. 2. 28. 2002년도 산재보험 확정보험료 및 2003년도 산재보험 개산보험료에 대한 자진신고를 하였고, 피청구인이 청구인이 신고한 보험료가 기재된 이 건 납부서를 청구인에게 발송(언제 청구인에게 발송하였는지 여부에 대하여는 확인이 되지 않음)하자, 청구인이 위 보험료를 2002. 3. 10. 자진납부한 사실이 인정되는바, 이와 같이 피청구인이 보험료 납부의무자의 보험관계 업무상 편의를 위하여 보험료부과내역이 적힌 이 건 납부서를 송부하였다 하더라도 이는 피청구인이 납부의무자로 하여금 자진납부하도록 안내한 것에 불과하다 할 것이어서 이 건 납부서의 교부가 피청구인이 자진신고·납부하지 아니한 사업주나 납부하여야 할 보험료에 미달하여 보험료를 납부한 사업주를 대상으로 하여 행하는 납부통지로서의 처분이라고 볼 수는 없다 할 것이다. 따라서 청구인의 이 건 납부고지에 대한 취소청구는 심판제기요건을 결한 부적법한 청구라 할 것이다.",
      "summ_pass": "피청구인이 보험료 납부의무자의 보험관계 업무상 편의를 위하여 보험료부과내역이 적힌 이 건 납부서를 송부하였다 하더라도 이는 피청구인이 납부의무자로 하여금 자진납부하도록 안내한 것에 불과하다 할 것이어서 이 건 납부서의 교부가 피청구인이 자진신고·납부하지 아니한 사업주나 납부하여야 할 보험료에 미달하여 보험료를 납부한 사업주를 대상으로 하여 행하는 납부통지로서의 처분이라고 볼 수는 없다 할 것이다. 따라서 청구인의 이 건 납부고지에 대한 취소청구는 심판제기요건을 결한 부적법한 청구라 할 것이다."
    }
  ],
  "keyword_tagg": [
    {
      "id": 1,
      "keyword": "심판제기요건"
    },
    {
      "id": 2,
      "keyword": "부적법한 청구"
    }
  ],
  "Reference_info": {
    "reference_rules": "행정심판법 제2조제1항, 제18조제1항 산업재해보상보험법 제65, 제67조",
    "reference_court_case": ""
  },
  "Class_info": {
    "class_name": "근로자",
    "instance_name": "산업재해보상보험료부과처분"
  }
}