{
  "info": {
    "id": 42010171,
    "dataType": "판결문",
    "caseNm": "과징금부과처분취소청구",
    "caseTitle": "국민권익위원회 2004-15958, 2005. 5. 9.",
    "courtType": "심결례",
    "courtNm": "국민권익위원회",
    "judmnAdjuDe": "2005-05-09",
    "caseNoID": "2004-15958",
    "caseNo": "2004-15958"
  },
  "jdgmn": "",
  "jdgmnInfo": [
    {
      "question": "동조제2항에 의하면 건설교통부장관 또는 시·도지사는 위반행위의 동기·내용 및 횟수 등을 참작하여 제1항의 규정에 의한 영업정지의 기간 또는 과징금의 금액의 2분의 1의 범위 안에서 이를 가중 또는 감경할 수 있다고 되어 있는가?",
      "answer": "긍정"
    }
  ],
  "Summary": [
    {
      "summ_contxt": "「건설산업기본법」 제2조에 의하면, 건설공사라 함은 토목공사·건축공사·산업설비공사·조경공사 및 환경시설공사등 시설물을 설치·유지·보수하는 공사(시설물을 설치하기 위한 부지조성공사를 포함한다), 기계설비 기타 구조물의 설치 및 해체공사등을 말한다고 되어 있고, 수급인이라 함은 발주자로부터 건설공사를 도급받은 건설업자를 말하며, 하도급관계에 있어서 하도급하는 건설업자를 포함한다고 되어 있으며, 동법 제8조제3항에 의하면, 전문건설업은 시설물의 일부 또는 전문분야에 관한 공사를 시공하는 건설업으로서 그 업종은 대통령령으로 정한다고 되어 있고, 동법 제29조제2항에 의하면, 수급인은 그가 도급받은 건설공사중 전문공사에 해당하는 건설공사를 하도급하고자 하는 때에는 당해 전문공사를 시공할 수 있는 전문건설업자에게 하도급하여야 한다고 되어 있으며, 동법 제82조, 제84조 및 동법 시행령 제80조제1항 별표6에 의하면, 건설교통부장관 또는 시·도지사는 건설업자가 법 제29조제2항의 하도급제한에 위반한 때에는 1년 이내의 기간을 정하여 당해 건설업자의 영업정지를 명하거나 영업정지에 갈음하여 그 위반한 공사의 도급금액(제2호의 경우에는 하도급금액을 말한다)의 100분의 30에 상당하는 금액이하의 과징금을 부과할 수 있다고 되어 있고, 동조제2항에 의하면 건설교통부장관 또는 시·도지사는 위반행위의 동기·내용 및 횟수 등을 참작하여 제1항의 규정에 의한 영업정지의 기간 또는 과징금의 금액의 2분의 1의 범위 안에서 이를 가중 또는 감경할 수 있다고 되어 있다.",
      "summ_pass": "1년 이내의 기간을 정하여 당해 건설업자의 영업정지를 명하거나 영업정지에 갈음하여 그 위반한 공사의 도급금액의 100분의 30에 상당하는 금액이하의 과징금을 부과할 수 있다고 되어 있고, 동조제2항에 의하면 건설교통부장관 또는 시·도지사는 위반행위의 동기·내용 및 횟수 등을 참작하여 제1항의 규정에 의한 영업정지의 기간 또는 과징금의 금액의 2분의 1의 범위 안에서 이를 가중 또는 감경할 수 있다고 되어 있다."
    }
  ],
  "keyword_tagg": [
    {
      "id": 1,
      "keyword": "건설산업기본법"
    },
    {
      "id": 2,
      "keyword": "시·도지사"
    }
  ],
  "Reference_info": {
    "reference_rules": "건설산업기본법 제2조, 제8조, 제29조제2항, 제82조, 제84조 및 제91조 건설산업기본법 시행령 제80조 및 별표 6",
    "reference_court_case": ""
  },
  "Class_info": {
    "class_name": "근로자",
    "instance_name": "행정처분취소"
  }
}