{
  "info": {
    "id": 38010486,
    "dataType": "판결문",
    "caseNm": "산업재해보상보험료부과처분취소청구",
    "caseTitle": "국민권익위원회 2004-03057, 2004. 5. 24.",
    "courtType": "심결례",
    "courtNm": "국민권익위원회",
    "judmnAdjuDe": "2004-05-24",
    "caseNoID": "2004-03057",
    "caseNo": "2004-03057"
  },
  "jdgmn": "",
  "jdgmnInfo": [
    {
      "question": "업종을 변경하고 이에 따라 추가되는 산재보험료 및 가산금을 부과한 처분은 위법·부당하다고 할 수 있는가?",
      "answer": "부정"
    }
  ],
  "Summary": [
    {
      "summ_contxt": "이 건 △△공장에서는 LCD모니터용 받침대 조립업무를 하고 있어 이 건 ○○공장과 이 건 △△공장의 업무가 시간적으로 서로 하나의 사업장으로 볼 수 있을 정도로 긴밀하게 연결되어 있다고 보기 어려운 점, 이 건 △△공장에서의 LCD모니터용 받침대 조립업무는 이 건 ○○공장에서 프레스 가공작업을 거친 금속부품들을 단순히 조립하는 일만 하는 것이어서 이를 컴퓨터나 그 주변기기 또는 관련 부품 등을 제조하는 사업과 동일한 것으로 보기는 어렵다 할 것인 점 등을 고려할 때, 이 건 △△공장은 이 건 ○○공장과는 별개의 사업장이며, 이 건 △△공장에서 행해지는 금속제품조립품 생산은 『기타제조업』 중 『기타각종제조업』에 해당한다고 할 것이다.\n(라) 따라서, 청구인 회사의 사업종류를 2001년도 7월 이전까지는 『전자제품제조업』에서 『금속제품제조업 또는 금속가공업』중 『기타금속제품제조업 또는 금속가공업』으로 변경하고, 2001년 8월 이후 청구인 회사의 사업장이 된 이 건 △△공장의 사업종류는 『전자제품제조업』에서 『기타제조업』중 『기타각종제조업』으로 변경하고 이에 따라 추가되는 산재보험료 및 가산금을 부과한 피청구인의 이 건 처분은 위법·부당하다고 할 수 없을 것이다.",
      "summ_pass": "청구인 회사의 사업종류를 2001년도 7월 이전까지는 『전자제품제조업』에서 『금속제품제조업 또는 금속가공업』중 『기타금속제품제조업 또는 금속가공업』으로 변경하고, 2001년 8월 이후 청구인 회사의 사업장이 된 이 건 △△공장의 사업종류는 『전자제품제조업』에서 『기타제조업』중 『기타각종제조업』으로 변경하고 이에 따라 추가되는 산재보험료 및 가산금을 부과한 피청구인의 이 건 처분은 위법·부당하다고 할 수 없을 것이다."
    }
  ],
  "keyword_tagg": [
    {
      "id": 1,
      "keyword": "기타금속제품제조업 또는 금속가공업"
    },
    {
      "id": 2,
      "keyword": "전자제품제조업"
    }
  ],
  "Reference_info": {
    "reference_rules": "산업재해보상보험법 제63조 동법시행령 제60조, 제61조제1항 및 제2항 동법시행규칙 제74조제2항",
    "reference_court_case": ""
  },
  "Class_info": {
    "class_name": "근로자",
    "instance_name": "산업재해보상보험료부과처분"
  }
}