{
  "info": {
    "id": 42009105,
    "dataType": "판결문",
    "caseNm": "재심 판정 처분 취소",
    "caseTitle": "서울행정법원 2008. 10. 24. 선고 2008구합6622 판결 : 항소",
    "courtType": "판례(하급심)",
    "courtNm": "서울행정법원",
    "judmnAdjuDe": "2008-10-24",
    "caseNoID": "2008구합6622",
    "caseNo": "2008구합6622"
  },
  "jdgmn": "[1] 전년도 경영실적평가에 따라 공공기관 임직원에게 지급한 성과상여금이 임의적·은혜적 성격의 금품이 아니라 근로의 대가로서 임금에 해당한다고 판단한 사례\n[2] 공공기관의 전년도 경영실적평가에 따른 성과상여금을 정규직 근로자들에게만 차등 지급하고 기간제 근로자들에게는 전혀 지급하지 않은 것은, 정규직 근로자와 기간제 근로자의 업무에 현저한 질적 차이가 있다고 보기 어려운 점 등에 비추어, ‘기간제 및 단시간근로자 보호 등에 관한 법률’ 제8조에서 금지하고 있는 ‘차별적 처우’에 해당한다고 한 사례",
  "jdgmnInfo": [
    {
      "question": "공공기관의 전년도 경영실적평가에 따른 성과상여금을 정규직 근로자들에게만 차등 지급하고 기간제 근로자들에게는 전혀 지급하지 않은 것이 ‘기간제 및 단시간근로자 보호 등에 관한 법률’ 제8조에서 금지하고 있는 ‘차별적 처우’에 해당하는가?",
      "answer": "긍정"
    }
  ],
  "Summary": [
    {
      "summ_contxt": "이 사건 제도에 의한 성과상여금은 원고의 내부규정상 ‘보수’의 한 항목으로 명시되어 있고, 한편 원고가 현재까지 위 내부규정(보수규정)을 정규직 근로자들에게만 적용하여 왔다는 점을 들어 이 사건 성과상여금의 객관적 성격이 정규직 근로자들과 기간제 근로자들에 있어서 각기 다르다고 볼 수는 없다.\n참가인들과 정규직 근로자들이 직제규정상 동일한 직명으로 근무하면서 어느 한 쪽이 교육·휴가 등으로 근무가 불가능할 경우에는 서로의 업무를 대신 수행한 점, 이들이 사업장에 따라서는 같은 작업조에 동등하게 소속되어 업무를 수행하기도 한 점 등에 비추어 보면, 이들의 업무 사이에는 그 핵심요소에 있어서 본질적 차이가 없는 것으로 보인다.\n성과상여금의 지급을 위하여 기존 인건비를 전환하지 아니하였고, 나아가 그 정규직 근로자들이 이를 위하여 특별한 부담을 진 사실에 관하여 다른 주장·입증이 없는 이상, 원고의 구체적 주장 취지와 무관하게 이 사건 성과상여금은 정규직 근로자의 임금을 재원으로 하였다고 볼 수 없고, 따라서 이와 다른 전제에서 이 사건 행위에 합리적인 이유가 있다고 볼 수도 없다.",
      "summ_pass": "경영실적평가에 따른 성과상여금의 성격은 근로의 대가로서 임금에 해당하는바, 정규직 근로자와 기간제 근로자의 업무에 현저한 질적 차이가 있다고 보기 어려운 점 등에 비추어, 공공기관의 전년도 경영실적평가에 따른 성과상여금을 정규직 근로자들에게만 차등 지급하고 기간제 근로자들에게는 전혀 지급하지 않은 것은 ‘기간제 및 단시간근로자 보호 등에 관한 법률’ 제8조에서 금지하고 있는 ‘차별적 처우’에 해당한다."
    }
  ],
  "keyword_tagg": [
    {
      "id": 1,
      "keyword": "성과상여금"
    },
    {
      "id": 2,
      "keyword": "기간제 근로자"
    }
  ],
  "Reference_info": {
    "reference_rules": "[1] 근로기준법 제2조 제1항 제5호 [2] 기간제 및 단시간근로자 보호 등에 관한 법률 제8조 제1항",
    "reference_court_case": ""
  },
  "Class_info": {
    "class_name": "근로자",
    "instance_name": "행정처분취소"
  }
}