{
  "info": {
    "id": 42010778,
    "dataType": "판결문",
    "caseNm": "임금등",
    "caseTitle": "대법원 2018. 6. 28. 선고 2012다106423 판결",
    "courtType": "판례(대법원)",
    "courtNm": "대법원",
    "judmnAdjuDe": "2018-06-28",
    "caseNoID": "2012다106423",
    "caseNo": "2012다106423"
  },
  "jdgmn": "휴일근로에 따른 가산임금과 연장근로에 따른 가산임금이 중복하여 지급될 수 있는지 여부(원칙적 소극)",
  "jdgmnInfo": [
    {
      "question": "특별한 사정이 없다면 휴일근로에 따른 가산임금과 연장근로에 따른 가산임금은 중복하여 지급될 수 없는가?",
      "answer": "긍정"
    }
  ],
  "Summary": [
    {
      "summ_contxt": "구 근로기준법 제50조 제1항, 제2항, 제53조 제1항, 제55조, 제56조, 근로기준법 시행령 제30조의 내용과 규정 체계, 구 근로기준법의 제·개정 연혁과 이를 통해 알 수 있는 입법취지와 목적, 근로관계 당사자들의 인식과 기존 노동관행, 개정 근로기준법 부칙 조항 등을 종합적으로 고려하면, 특별한 사정이 없는 한 휴일근로에 따른 가산임금과 연장근로에 따른 가산임금은 중복하여 지급될 수 없다고 보아야 한다.",
      "summ_pass": "구 근로기준법의 내용과 규정 체계, 입법취지와 목적, 근로관계 당사자들의 인식과 기존 노동관행, 개정 근로기준법 부칙 조항 등을 종합적으로 고려하면, 특별한 사정이 없는 한 휴일근로에 따른 가산임금과 연장근로에 따른 가산임금은 중복하여 지급될 수 없다."
    }
  ],
  "keyword_tagg": [
    {
      "id": 1,
      "keyword": "근로기준법"
    },
    {
      "id": 2,
      "keyword": "입법취지"
    },
    {
      "id": 3,
      "keyword": "근로관계"
    },
    {
      "id": 4,
      "keyword": "가산임금"
    },
    {
      "id": 5,
      "keyword": "휴일근로"
    },
    {
      "id": 6,
      "keyword": "연장근로"
    },
    {
      "id": 7,
      "keyword": "임금"
    }
  ],
  "Reference_info": {
    "reference_rules": "구 근로기준법(2018. 3. 20. 법률 제15513호로 개정되기 전의 것) 제50조 제1항, 제2항, 제53조 제1항, 제55조(현행 제55조 제1항 참조), 제56조, 근로기준법 제2조 제1항 제7호, 제53조 제3항, 부칙(2018. 3. 20.) 제1조 제2항, 제3항, 제2조, 구 근로기준법 시행령(2018. 6. 29. 대통령령 제29010호로 개정되기 전의 것) 제30조(현행 제30조 제1항 참조)",
    "reference_court_case": "대법원 2018. 6. 21. 선고 2011다112391 전원합의체 판결(공2018하, 1359)"
  },
  "Class_info": {
    "class_name": "근로자",
    "instance_name": "임금"
  }
}