{
  "info": {
    "id": 41009803,
    "dataType": "판결문",
    "caseNm": "장해급여부지급처분취소",
    "caseTitle": "대법원 2019. 4. 25. 선고 2015두39897 판결",
    "courtType": "판례(대법원)",
    "courtNm": "대법원",
    "judmnAdjuDe": "2019-04-25",
    "caseNoID": "2015두39897",
    "caseNo": "2015두39897"
  },
  "jdgmn": "[1] 소멸시효 중단사유인 채무 승인의 방법 / 채무 승인이 성립하기 위해서는 채무자가 권리 등의 법적 성질을 알고 있거나 권리 등의 발생원인을 특정하여야 하는지 여부(소극) 및 채무 승인이 있는지 판단하는 방법\n[2] 산업재해보상보험법 제113조는 같은 법 제36조 제2항에 따른 보험급여 청구를 민법상의 시효중단 사유와는 별도의 고유한 시효중단 사유로 정한 것인지 여부(적극) 및 위 보험급여 청구에 따른 시효중단은 근로복지공단의 결정이 있은 때 중단사유가 종료되어 새로이 3년의 시효기간이 진행되는지 여부(적극)\n[3] 산업재해보상보험법상 고유한 시효중단 사유인 보험급여 청구에 따른 시효중단의 효력은 보험급여 결정에 대한 임의적 불복절차인 심사 청구나 재심사 청구에 따른 시효중단의 효력과는 별개로 존속하는지 여부(적극)",
  "jdgmnInfo": [
    {
      "question": "채무 승인이 성립하기 위해서는 채무자가 권리 등의 법적 성질을 알고 있거나 권리 등의 발생원인을 특정하여야 하는가?",
      "answer": "부정"
    }
  ],
  "Summary": [
    {
      "summ_contxt": "소멸시효 중단사유인 채무 승인은 시효이익을 받는 당사자인 채무자가 소멸시효 완성으로 채권을 상실하게 될 상대방 또는 그 대리인에 대하여 상대방의 권리 또는 자신의 채무가 있음을 알고 있다는 뜻을 표시함으로써 성립하며, 그 표시의 방법은 특별한 형식이 필요하지 않고 묵시적이든 명시적이든 상관없다. 또한 승인은 시효이익을 받는 채무자가 상대방의 권리 등의 존재를 인정하는 일방적 행위로서, 권리의 원인·내용이나 범위 등에 관한 구체적 사항을 확인하여야 하는 것은 아니고, 채무자가 권리 등의 법적 성질까지 알고 있거나 권리 등의 발생원인을 특정하여야 할 필요는 없다.",
      "summ_pass": "인은 시효이익을 받는 채무자가 상대방의 권리 등의 존재를 인정하는 일방적 행위로서, 권리의 원인·내용이나 범위 등에 관한 구체적 사항을 확인하여야 하는 것은 아니고, 채무자가 권리 등의 법적 성질까지 알고 있거나 권리 등의 발생원인을 특정하여야 할 필요는 없다."
    }
  ],
  "keyword_tagg": [
    {
      "id": 1,
      "keyword": "소멸시효 중단사유"
    },
    {
      "id": 2,
      "keyword": "시효 완성"
    }
  ],
  "Reference_info": {
    "reference_rules": "[1] 민법 제168조 [2] 산업재해보상보험법 제36조 제2항, 제112조, 제113조 / 민법 제178조 제1항 [3] 산업재해보상보험법 제36조 제2항, 제103조, 제106조, 제111조, 제112조, 제113조 / 민법 제170조",
    "reference_court_case": "[1] 대법원 2008. 7. 24. 선고 2008다25299 판결(공2008하, 1239), 대법원 2012. 10. 25. 선고 2012다45566 판결(공2012하, 1921) [2] 대법원 1995. 5. 12. 선고 94다24336 판결(공1995상, 2101), 대법원 2006. 6. 16. 선고 2005다25632 판결(공2006하, 1327), 대법원 2018. 6. 15. 선고 2017두49119 판결(공2018하, 1308)"
  },
  "Class_info": {
    "class_name": "근로자",
    "instance_name": "장해급여"
  }
}