{
  "info": {
    "id": 42009822,
    "dataType": "판결문",
    "caseNm": "건설산업기본법위반",
    "caseTitle": "대법원 2022. 2. 24. 선고 2018도3821 판결",
    "courtType": "판례(대법원)",
    "courtNm": "대법원",
    "judmnAdjuDe": "2022-02-24",
    "caseNoID": "2018도3821",
    "caseNo": "2018도3821"
  },
  "jdgmn": "[1] 구 건설산업기본법상 건설업 등록제도의 취지 / 건설업 등록의무가 면제되는 ‘경미한 건설공사’ 중 하나로 공사예정금액이 1,500만 원 미만인 전문 건설공사를 정한 구 건설산업기본법 시행령 제8조 제1항의 해석과 관련하여 분할 발주된 수 개의 공사가 ‘동일한 공사’로서 공사예정금액 합산 대상에 해당하는지 판단하는 기준\n[2] 산업재해보상보험법 및 고용보험법에서 정한 ‘총공사금액’의 판단 기준을 구 건설산업기본법 시행령 제8조 제1항에서 정한 ‘동일한 공사’의 해석에 유추적용할 수 있는지 여부(소극)",
  "jdgmnInfo": [
    {
      "question": "산업재해보상보험법 및 고용보험법에서 정한 ‘총공사금액’의 판단 기준을 구 건설산업기본법 시행령 제8조 제1항에서 정한 ‘동일한 공사’의 해석에 유추적용할 수 있는가?",
      "answer": "부정"
    }
  ],
  "Summary": [
    {
      "summ_contxt": "구 건설산업기본법 제9조 제1항 본문은 “건설업을 하려는 자는 대통령령이 정하는 업종별로 국토교통부장관에게 등록을 하여야 한다.”라고 규정하면서, 제96조 제1호에서 “제9조 제1항에 따른 등록을 하지 아니하거나 부정한 방법으로 등록을 하고 건설업을 한 자”에 대한 처벌규정을 두고 있는바, 이러한 건설업 등록제도의 취지는 건설공사의 적정한 시공과 건설산업의 건전한 발전을 도모하고 무등록업자에 의한 부실시공을 예방하여 국민의 생명과 재산을 보호하고자 하는 것이다. 한편 구 건설산업기본법 제9조 제1항 단서는 건설업 등록제도의 예외로서 “대통령령으로 정하는 경미한 건설공사를 업으로 하려는 경우에는 등록을 하지 아니하고 건설업을 할 수 있다.”라고 정하고 있고, 구 건설산업기본법 시행령 제8조 제1항은 이러한 ‘경미한 건설공사’ 중 하나로 공사예정금액이 1,500만 원 미만인 전문 건설공사를 정하면서, 동일한 공사를 2 이상의 계약으로 분할하여 발주하는 경우에는 각각의 공사예정금액을 합산한 금액을 공사예정금액으로 하도록 정하고 있다. 이러한 건설업 등록제도의 취지와 관련 규정의 내용 등에 비추어 볼 때, 분할 발주된 수 개의 공사가 ‘동일한 공사’로서 공사예정금액 합산 대상에 해당하는지 여부는 각 공사계약의 당사자, 공사 목적물, 공사기간, 공사 내용 및 방법, 수 개의 계약으로 분할하여 체결한 경위 등 제반 사정들을 종합적으로 고려하여, 실질적으로 각 공사계약이 하나의 계약으로서 각 공사 사이에 동일성이 인정되는지 여부를 기준으로 판단하여야 한다. 반면 당사자들이 수 개의 공사에 대하여 하나의 공사계약을 체결하였다고 하더라도 각 공사가 목적물, 내용이나 시공방법 등을 달리하여 실질적으로 하나의 공사로 볼 수 없는 경우에는 이를 ‘동일한 공사’로 평가할 수 없을 것이다.",
      "summ_pass": "건설업 등록제도의 취지와 관련 규정의 내용 등에 비추어 볼 때, 분할 발주된 수 개의 공사가 ‘동일한 공사’로서 공사예정금액 합산 대상에 해당하는지 여부는 각 공사계약의 당사자, 공사 목적물, 공사기간, 공사 내용 및 방법, 수 개의 계약으로 분할하여 체결한 경위 등 제반 사정들을 종합적으로 고려하여, 실질적으로 각 공사계약이 하나의 계약으로서 각 공사 사이에 동일성이 인정되는지 여부를 기준으로 판단하여야 한다. 반면 당사자들이 수 개의 공사에 대하여 하나의 공사계약을 체결하였다고 하더라도 각 공사가 목적물, 내용이나 시공방법 등을 달리하여 실질적으로 하나의 공사로 볼 수 없는 경우에는 이를 ‘동일한 공사’로 평가할 수 없을 것이다."
    }
  ],
  "keyword_tagg": [
    {
      "id": 1,
      "keyword": "건설업"
    },
    {
      "id": 2,
      "keyword": "공사계약"
    }
  ],
  "Reference_info": {
    "reference_rules": "[1] 구 건설산업기본법(2017. 3. 21. 법률 제14708호로 개정되기 전의 것) 제9조 제1항, 제96조 제1호(현행 제95조의2 제1호 참조), 구 건설산업기본법 시행령(2020. 12. 29. 대통령령 제31328호로 개정되기 전의 것) 제8조 제1항 [2] 산업재해보상보험법 제6조, 구 산업재해보상보험법 시행령(2017. 12. 16. 대통령령 제28506호로 개정되기 전의 것) 제2조 제1항 제3호 (가)목(현행 삭제), 고용보험법 제8조 제1항, 고용보험법 시행령 제2조 제1항 제2호 (가)목, 고용보험 및 산업재해보상보험의 보험료징수 등에 관한 법률 시행령 제2조 제1항 제2호, 제2항 / 구 건설산업기본법 시행령(2020. 12. 29. 대통령령 제31328호로 개정되기 전의 것) 제8조 제1항",
    "reference_court_case": ""
  },
  "Class_info": {
    "class_name": "근로자",
    "instance_name": "건설"
  }
}