{
  "info": {
    "id": 41010887,
    "dataType": "판결문",
    "caseNm": "[공정대표의무 위반 및 부당해고구제재심 판정 취소]상고",
    "caseTitle": "서울고등법원 2019. 7. 10. 선고 2018누73708 판결",
    "courtType": "판례(하급심)",
    "courtNm": "서울고등법원",
    "judmnAdjuDe": "2019-07-10",
    "caseNoID": "2018누73708",
    "caseNo": "2018누73708"
  },
  "jdgmn": "",
  "jdgmnInfo": [
    {
      "question": "제2 노조가 2017년 단체협약체결 후에 자신에게도 노동조합 사무실을 제공할 것을 C에 주장함으로써 노조사무실사용합의와 그에 따라 형성되어 가던 노사 관행이 더는 유지될 수 없게 되었다. 하지만, 이런 사정은 2017년 단체협약 체결 후에 비로소 발생한 사정으로서 장래에 향하여 효력을 발생할 뿐이고 이와 달리 소급하여 2017년 단체협약의 해당 부분 조항을 무효화로 한다고 볼 수 있는가?",
      "answer": "부정"
    }
  ],
  "Summary": [
    {
      "summ_contxt": "C와 3개의 복수 노동조합이 서로 양해하여 자율적으로 노조사무실 사용합의에 이르렀고(다만 이로써 3개의 복수 노동조합이 노조사무실 사용에 관한 권리를 확정적으로 포기했다고 볼 것은 아니다), 그 사용합의에 따라 그때부터 2017년 단체협약 체결 당시까지 사이에 노조사무실 제공 및 사용방법에 관한 노사 관행이 점차 형성되어 가고 있었다고 봄이 타당하다. 다만, 제2 노조가 2017년 단체협약체결 후에 자신에게도 노동조합 사무실을 제공할 것을 C에 주장함으로써 노조사무실사용합의와 그에 따라 형성되어 가던 노사 관행이 더는 유지될 수 없게 되었다. 하지만, 이런 사정은 2017년 단체협약 체결 후에 비로소 발생한 사정으로서 장래에 향하여 효력을 발생할 뿐이고 이와 달리 소급하여 2017년 단체협약의 해당 부분 조항을 무효화로 한다고 볼 수는 없다.",
      "summ_pass": "제2 노조가 2017년 단체협약체결 후에 자신에게도 노동조합 사무실을 제공할 것을 C에 주장함으로써 노조사무실사용합의와 그에 따라 형성되어 가던 노사 관행이 더는 유지될 수 없게 되었다. 하지만, 이런 사정은 2017년 단체협약 체결 후에 비로소 발생한 사정으로서 장래에 향하여 효력을 발생할 뿐이고 이와 달리 소급하여 2017년 단체협약의 해당 부분 조항을 무효화로 한다고 볼 수는 없다."
    }
  ],
  "keyword_tagg": [
    {
      "id": 1,
      "keyword": "무효"
    }
  ],
  "Reference_info": {
    "reference_rules": "근로기준법",
    "reference_court_case": ""
  },
  "Class_info": {
    "class_name": "근로자",
    "instance_name": "근로기준법"
  }
}