{
  "info": {
    "id": 41010809,
    "dataType": "판결문",
    "caseNm": "근로기준법위반",
    "caseTitle": "대구지방법원 2022. 1. 11. 선고 2021노2970 판결",
    "courtType": "판례(하급심)",
    "courtNm": "대구지방법원",
    "judmnAdjuDe": "2022-01-11",
    "caseNoID": "2021노2970",
    "caseNo": "2021노2970"
  },
  "jdgmn": "",
  "jdgmnInfo": [
    {
      "question": "하도급계약이 해지되었다고 인정하기는 어렵다면, 계속 유지되었던 것으로 인정되는 것이 합당한가?",
      "answer": "긍정"
    }
  ],
  "Summary": [
    {
      "summ_contxt": "N이 검찰수사관과의 전화통화에서, ‘공사대금 문제로 2019. 6. 말경 하도급 공사에 더 이상 관여하지 않았고, 별도의 하도급 공사 해지 서류를 작성하지는 않았다’는 취지로 진술한 사실은 있으나(증거기록 220쪽), 2019. 6. 말 이후인 2019. 9.까지도 E로 공사대금을 지급하였고(증거기록 196쪽), E에서도 그에 상응하는 전자세금계산서를 발급해 준 사실이 인정되는 점(증거기록 27쪽), 2019. 6. 말 이후에도 A와 F 사이의 구체적인 업무내용이 종전과 달라진 것은 없었던 것으로 보이는 점에 비추어 보면, 위와 같은 N의 진술만으로 2019. 6. 말경 F과 E 사이의 하도급계약이 해지되었다고 인정하기는 어렵고, 계속 유지되었던 것으로 인정된다.",
      "summ_pass": "E에서도 그에 상응하는 전자세금계산서를 발급해 준 사실이 인정되는 점(증거기록 27쪽), 2019. 6. 말 이후에도 A와 F 사이의 구체적인 업무내용이 종전과 달라진 것은 없었던 것으로 보이는 점에 비추어 보면, 위와 같은 N의 진술만으로 2019. 6. 말경 F과 E 사이의 하도급계약이 해지되었다고 인정하기는 어렵고, 계속 유지되었던 것으로 인정된다."
    }
  ],
  "keyword_tagg": [
    {
      "id": 1,
      "keyword": "전자세금계산서"
    },
    {
      "id": 2,
      "keyword": "하도급계약"
    }
  ],
  "Reference_info": {
    "reference_rules": "",
    "reference_court_case": ""
  },
  "Class_info": {
    "class_name": "근로자",
    "instance_name": "근로기준법위반"
  }
}