{
  "info": {
    "id": 42009668,
    "dataType": "판결문",
    "caseNm": "임금",
    "caseTitle": "대법원 2022. 4. 14. 선고 2021다280781 판결",
    "courtType": "판례(대법원)",
    "courtNm": "대법원",
    "judmnAdjuDe": "2022-04-14",
    "caseNoID": "2021다280781",
    "caseNo": "2021다280781"
  },
  "jdgmn": "[1] 근로기준법 제94조 제1항 단서에서 정한 ‘취업규칙의 불이익한 변경’의 의미 및 그 대상인 근로조건이나 복무규율에 관한 근로자의 권리나 이익은 종전 취업규칙의 보호영역에 따라 보호되는 직접적이고 구체적인 이익인지 여부(적극)\n[2] 甲 학교법인이 운영하는 대학교의 교직원보수규정에서 예산의 범위에서 교원에게 연구보조비를 지급한다고 정하고 있고, 매 학년도별 봉급과 각종 수당의 세부 항목과 액수 등을 정한 교직원 보수표에서 연구보조비 액수를 정하고 있는데, 甲 법인이 일부 학년도의 연구보조비를 직전 학년도보다 적게 정한 것이 취업규칙의 불이익한 변경에 해당하는지 문제 된 사안에서, 甲 법인이 매 학년도에 정한 연구보조비 액수가 매 학년도의 교직원 보수표의 보호영역에 따라 보호되는 직접적이고 구체적인 이익이라고 보기 어렵고, 일부 학년도의 연구보조비 액수가 직전 학년도에 비해 줄어든 것을 실질적으로 연구보조비에 관한 종전 취업규칙을 교원에게 불리하게 개정하거나 변경한 것이라고 단정할 수 없다고 한 사례\n[3] 재판상 자백의 의미 및 상대방의 주장에 단순히 침묵하거나 불분명한 진술을 하는 것만으로 자백이 있다고 인정할 수 있는지 여부(소극) / 자백간주가 성립하지 않는 경우로서 변론 전체의 취지로 보아 당사자가 상대방이 주장하는 사실을 다툰 것으로 볼 것인지 판단하는 방법 / 법률상의 주장에 대하여 재판상 자백 또는 자백간주가 적용되는지 여부(소극)\n[4] 명예퇴직수당이 후불임금이나 퇴직급여에 해당하지 않는 경우, 그에 대한 지연손해금을 계산할 때 근로기준법 제37조 제1항과 근로기준법 시행령 제17조가 적용되는지 여부(소극)",
  "jdgmnInfo": [
    {
      "question": "상대방의 주장에 단순히 침묵하거나 불분명한 진술을 하는 것만으로 자백이 있다고 인정할 수 있는가?",
      "answer": "부정"
    }
  ],
  "Summary": [
    {
      "summ_contxt": "재판상 자백은 변론기일 또는 변론준비기일에서 상대방의 주장과 일치하면서 자신에게는 불리한 사실을 진술하는 것을 말하며, 상대방의 주장에 단순히 침묵하거나 불분명한 진술을 하는 것만으로는 자백이 있다고 인정하기에 충분하지 않다. 당사자가 변론에서 상대방이 주장하는 사실을 명백히 다투지 않았더라도 변론 전체의 취지로 보아 다툰 것으로 인정되는 때에는 자백간주가 성립하지 않는다(민사소송법 제150조 제1항 참조). 여기서 변론 전체의 취지로 보아 다투었다고 볼 것인지는 변론종결 당시까지 당사자가 한 주장 취지와 소송의 경과를 전체적으로 종합해서 판단해야 한다. 자백간주 역시 재판상 자백의 경우와 마찬가지로 상대방의 사실에 관한 주장에 대해서만 적용되고, 법률상의 주장에 대해서는 적용되지 않는다.",
      "summ_pass": "재판상 자백은 변론기일 또는 변론준비기일에서 상대방의 주장과 일치하면서 자신에게는 불리한 사실을 진술하는 것을 말하며, 상대방의 주장에 단순히 침묵하거나 불분명한 진술을 하는 것만으로는 자백이 있다고 인정하기에 충분하지 않다."
    }
  ],
  "keyword_tagg": [
    {
      "id": 1,
      "keyword": "자백"
    }
  ],
  "Reference_info": {
    "reference_rules": "[1] 근로기준법 제94조 제1항 [2] 근로기준법 제94조 제1항, 사립학교법 제30조, 제31조 제1항 [3] 민사소송법 제150조 제1항, 제288조 [4] 근로기준법 제36조, 제37조 제1항, 근로기준법 시행령 제17조",
    "reference_court_case": "[1] 대법원 1993. 8. 24. 선고 93다17898 판결(공1993하, 2606), 대법원 2022. 3. 17. 선고 2020다219928 판결 [3] 대법원 1973. 10. 10. 선고 73다907 판결, 대법원 2013. 3. 28. 선고 2011다62274 판결, 대법원 2021. 7. 29. 선고 2018다267900 판결 [4] 대법원 2000. 7. 7. 선고 98다42172 판결(공2000하, 1874), 대법원 2007. 11. 29. 선고 2005다28358 판결(공2007하, 1993)"
  },
  "Class_info": {
    "class_name": "근로자",
    "instance_name": "임금"
  }
}