{
  "info": {
    "id": 42009738,
    "dataType": "판결문",
    "caseNm": "임금",
    "caseTitle": "대법원 2021. 6. 10. 선고 2021다217370 판결",
    "courtType": "판례(대법원)",
    "courtNm": "대법원",
    "judmnAdjuDe": "2021-06-10",
    "caseNoID": "2021다217370",
    "caseNo": "2021다217370"
  },
  "jdgmn": "[1] 직상 수급인의 임금지급 연대책임을 규정하고 있는 근로기준법 제44조의2가 강행규정인지 여부(적극)\n[2] 건설근로자가 소송 상대방과의 고용관계를 주장하며 임금청구를 하는 경우, 이를 심리하는 사실심법원이 유의하여야 할 사항",
  "jdgmnInfo": [
    {
      "question": "직상 수급인의 임금지급 연대책임을 규정하고 있는 근로기준법 제44조의2가 강행규정인가?",
      "answer": "긍정"
    }
  ],
  "Summary": [
    {
      "summ_contxt": "이는 직상 수급인이 건설업 등록이 되어 있지 않아 건설공사를 위한 자금력 등이 확인되지 않는 자에게 건설공사를 하도급하는 위법행위를 함으로써 하수급인의 임금지급의무 불이행에 관한 추상적 위험을 야기한 잘못에 대하여 실제로 하수급인이 임금지급의무를 이행하지 않아 이러한 위험이 현실화되었을 때 책임을 묻는 취지로서, 건설 하도급 관계에서 발생하는 임금지급방식을 개선하여 건설근로자의 권리를 보장할 수 있도록 하는 데 입법 취지를 두고 있다. 또한 근로기준법 제109조 제1항은 근로기준법 제44조의2를 위반하여 임금지급의무를 불이행한 직상 수급인에 대해 형사처벌을 하도록 정하고 있는바, 이와 같은 입법 취지, 규정 내용과 형식 등을 종합하여 보면 근로기준법 제44조의2는 개인의 의사에 의하여 적용을 배제할 수 없는 강행규정으로 봄이 타당하고 따라서 이를 배제하거나 잠탈하는 약정을 하였더라도 그 약정은 효력이 없다.",
      "summ_pass": "근로기준법 제109조 제1항은 근로기준법 제44조의2를 위반하여 임금지급의무를 불이행한 직상 수급인에 대해 형사처벌을 하도록 정하고 있는바, 이와 같은 입법 취지, 규정 내용과 형식 등을 종합하여 보면 근로기준법 제44조의2는 개인의 의사에 의하여 적용을 배제할 수 없는 강행규정으로 봄이 타당하고 따라서 이를 배제하거나 잠탈하는 약정을 하였더라도 그 약정은 효력이 없다."
    }
  ],
  "keyword_tagg": [
    {
      "id": 1,
      "keyword": "임금"
    },
    {
      "id": 2,
      "keyword": "근로기준법"
    },
    {
      "id": 3,
      "keyword": "강행규정"
    }
  ],
  "Reference_info": {
    "reference_rules": "[1] 근로기준법 제44조의2, 제109조 제1항 [2] 민사소송법 제203조, 근로기준법 제44조의2",
    "reference_court_case": "[1] 대법원 2019. 10. 31. 선고 2018도9012 판결(공2019하, 2292) [2] 대법원 2017. 9. 12. 선고 2017다865 판결(공2017하, 1952)"
  },
  "Class_info": {
    "class_name": "근로자",
    "instance_name": "임금"
  }
}