{
  "info": {
    "id": 53493161,
    "dataType": "판결문",
    "caseNm": "개인택시운송사업면허취소처분청구사건",
    "caseTitle": "서울고법 1986. 6. 20., 선고, 85구1228, 제4특별부판결 : 확정",
    "courtType": "판례(하급심)",
    "courtNm": "서울고법",
    "judmnAdjuDe": "1986-06-20",
    "caseNoID": "85구1228",
    "caseNo": "85구1228"
  },
  "jdgmn": "운수회사의 노동조합장직에 있는 기간도 개인택시 면허신청을 위한 운전경력기간에 포함되는지 여부",
  "jdgmnInfo": [
    {
      "question": "운수회사의 노동조합장직에 있는 기간도 개인택시 면허신청을 위한 운전경력기간에 포함되는가?",
      "answer": "긍정"
    }
  ],
  "Summary": [
    {
      "summ_contxt": "운수회사의 노동조합장직에 있으면서 전속적으로 택시를 배차받아 운전을 하지 아니하였다 할지라도 사고등으로 운전상 유고시 수시로 사고차량을 운전하는 등 사실상 운전업무에 종사하였다면 그 기간도 개인택시 면허신청을 위한 운전경력기간에 포함된다고 봄이 타당하다.",
      "summ_pass": "사고등으로 운전상 유고시 수시로 사고차량을 운전하는 등 사실상 운전업무에 종사하였다면 그 기간도 개인택시 면허신청을 위한 운전경력기간에 포함된다고 봄이 타당하다."
    }
  ],
  "keyword_tagg": [
    {
      "id": 1,
      "keyword": "개인택시운송사업면허취소처분"
    }
  ],
  "Reference_info": {
    "reference_rules": "자동차운수사업법 제4조, 자동차운수사업법시행규칙 제15조",
    "reference_court_case": ""
  },
  "Class_info": {
    "class_name": "근로자",
    "instance_name": "개인택시운송사업면허취소처분청구사건"
  }
}