{
  "info": {
    "id": 41010674,
    "dataType": "판결문",
    "caseNm": "해고무효확인",
    "caseTitle": "대법원 1992. 4. 24. 선고 91다17931 판결",
    "courtType": "판례(대법원)",
    "courtNm": "대법원",
    "judmnAdjuDe": "1992-04-24",
    "caseNoID": "91다17931",
    "caseNo": "91다17931"
  },
  "jdgmn": "가. 택시회사 운전기사가 배차받은 차량이 불결하다는 이유로 운행을 거부한 행위는 단체협약과 취업규칙에 정한 해고사유에 해당되지 않으나, 계속 반복된 근무해태, 무단결근 등 다른 징계사유들만으로도 동인에 대한 해고가 정당하다고 한 사례\n나. 근로자가 질병이나 부상 등으로 인하여 근무할 수 없는 경우에 근무해태가 정당화되기 위한 절차\n다. 단체협약상의 근로시간에 시간외 근로가 포함되어 있고 근로자들이 시간외 근로를 하였는데도 사용자가 시간외 근로수당을 지급하지 않는다는 사유 때문에 근로자의 불성실근무에 대한 징계해고가 형평의 원칙에 반하는 것인지 여부(소극)\n라. 취업규칙에 따른 해고와 근로기준법 제27조 소정의 “정당한 이유”",
  "jdgmnInfo": [
    {
      "question": "단체협약상의 근로시간에 시간외 근로가 포함되어 있고 근로자들이 시간외 근로를 하였는데도 사용자가 시간외 근로수당을 지급하지 않는다는 사유 때문에 근로자의 불성실근무에 대한 징계해고가 형평의 원칙에 반하는 것인가?",
      "answer": "부정"
    }
  ],
  "Summary": [
    {
      "summ_contxt": "단체협약에서 정한 근로시간에 시간외 근로가 포함되어 있고 근로자들이 시간외 근로를 하였는데도 사용자가 이에 대한 수당을 지급하지 않는 경우에는 적법한 절차에 따라 이의 지급을 구함은 별론으로 하고, 사용자가 위 수당을 지급하지 아니하였다는 사유를 들어 근로자의 불성실한 근무가 정당화되는 것은 아니므로 불성실근무에 대한 징계해고가 형평의 원칙에 반한다고 할 수도 없다.",
      "summ_pass": "사용자가 위 수당을 지급하지 아니하였다는 사유를 들어 근로자의 불성실한 근무가 정당화되는 것은 아니므로 불성실근무에 대한 징계해고가 형평의 원칙에 반한다고 할 수도 없다."
    }
  ],
  "keyword_tagg": [
    {
      "id": 1,
      "keyword": "형평의 원칙"
    },
    {
      "id": 2,
      "keyword": "적법한 절차"
    }
  ],
  "Reference_info": {
    "reference_rules": "근로기준법 제27조 제1항",
    "reference_court_case": "가. 대법원 1989. 12. 26. 선고 89누589 판결(공1990,411), 대법원 1991. 11. 22. 선고 91누4102 판결(공1992,320), 대법원 1991. 11. 22. 선고 91다6740 판결(공1992,259) 라. 대법원 1990. 12. 7. 선고 90다카23912 판결(공1991,437), 대법원 1991. 3. 27. 선고 90다카25420 판결(공1991,1273), 대법원 1991. 10. 11. 선고 91다20173 판결(공1991,2706)"
  },
  "Class_info": {
    "class_name": "근로자",
    "instance_name": "해고무효"
  }
}