{
  "info": {
    "id": 41010644,
    "dataType": "판결문",
    "caseNm": "해고무효확인등",
    "caseTitle": "대법원 1993. 1. 26. 선고 92다11695 판결",
    "courtType": "판례(대법원)",
    "courtNm": "대법원",
    "judmnAdjuDe": "1993-01-26",
    "caseNoID": "92다11695",
    "caseNo": "92다11695"
  },
  "jdgmn": "가. 이른바 전적의 의미와 근로자의 동의가 전적의 유효요건인지 여부(한정적극) 및 근로자의 동의 없이 전적시키는 관행이 근로계약의 내용을 이루고 있다고 인정하기 위한 요건\n나. 기업그룹 내부의 전적에 관하여 근로자의 포괄적인 사전동의로써 전적시킬 수 있는지 여부(적극)\n다. 사용자가 기업그룹 내의 전적에 관하여 근로자의 포괄적인 사전동의를 받는 경우의 동의방법",
  "jdgmnInfo": [
    {
      "question": "기업그룹 내부의 전적에 관하여 근로자의 포괄적인 사전동의로써 전적시킬 수 있는가?",
      "answer": "긍정"
    }
  ],
  "Summary": [
    {
      "summ_contxt": "근로자의 동의를 전적의 요건으로 하는 이유는 근로관계에 있어서 업무지휘권의 주체가 변경됨으로 인하여 근로자가 받을 불이익을 방지하려는 데에 있다고 할 것인바, 그룹 내의 기업에 고용된 근로자를 다른 계열기업으로 전적시키는 것은 형식적으로는 사용자의 법인격이 달라지게 된다 하더라도 실질적으로 업무지휘권의 주체가 변동된 것으로 보기 어려운 면이 있으므로, 사용자가 기업그룹 내부의 전적에 관하여 미리(근로자가 입사할 때 또는 근무하는 동안에) 근로자의 포괄적인 동의를 얻어 두면 그때마다 근로자의 동의를 얻지 아니하더라도 근로자를 다른 계열기업으로 유효하게 전적시킬 수 있다.",
      "summ_pass": "사용자가 기업그룹 내부의 전적에 관하여 미리(근로자가 입사할 때 또는 근무하는 동안에) 근로자의 포괄적인 동의를 얻어 두면 그때마다 근로자의 동의를 얻지 아니하더라도 근로자를 다른 계열기업으로 유효하게 전적시킬 수 있다."
    }
  ],
  "keyword_tagg": [
    {
      "id": 1,
      "keyword": "포괄적인 동의"
    },
    {
      "id": 2,
      "keyword": "근로자의 동의"
    }
  ],
  "Reference_info": {
    "reference_rules": "민법 제657조 제1항, 근로기준법 제27조 제1항",
    "reference_court_case": "가.나.다. 대법원 1993. 1. 26. 선고 92누8200 판결(공1993,868) 가. 대법원 1989. 5. 9. 선고 88다카4918 판결(공1989,892)"
  },
  "Class_info": {
    "class_name": "근로자",
    "instance_name": "해고무효확인등"
  }
}