{
  "info": {
    "id": 41009569,
    "dataType": "판결문",
    "caseNm": "근로기준법위반",
    "caseTitle": "대법원 1994. 5. 27. 선고 93도3377 판결",
    "courtType": "판례(대법원)",
    "courtNm": "대법원",
    "judmnAdjuDe": "1994-05-27",
    "caseNoID": "93도3377",
    "caseNo": "93도3377"
  },
  "jdgmn": "가. 근로기준법 제27조 제1항 위반죄(근로기준법 제107조 해당죄)의 성립에 고의를 필요로 하는지 여부\n나. 사용자가 근로자에게 당해 징계처분을 할 만한 정당한 이유가 있다고 판단한 것이 무리가 아니었다고 인정되는 경우 근로기준법 제27조 제1항 위반죄의 고의를 인정할 수 있는지 여부",
  "jdgmnInfo": [
    {
      "question": "사용자가 근로자에게 당해 징계처분을 할 만한 정당한 이유가 있다고 판단한 것이 무리가 아니었다고 인정되는 경우, 근로기준법 제27조 제1항 위반죄의 고의를 인정할 수 있는가?",
      "answer": "부정"
    }
  ],
  "Summary": [
    {
      "summ_contxt": "가. 형법 제13조 단서에서 말하는 특별한 규정이 있는 경우라 함은 다른 형벌법규에 의하여 처벌하는 죄의 성립에 고의를 요하지 아니한다는 명문의 규정이 있거나 그 법률규정 중에 그러한 취지를 명백하게 알 수 있는 경우를 의미하므로, 이와 같은 특별한 규정이 있는 경우에 해당하는 것으로 인정되지 아니하는 근로기준법 제107조에 의하여 처벌되는 같은 법 제27조 제1항 위반죄에 있어서는 일반형벌의 원칙에 따라 고의를 필요로 한다.\n나. 어떤 징계사유가 존재하고 당시 사정으로 보아 사용자가 당해 징계처분을 할 만한 정당한 이유가 있다고 판단한 것이 무리가 아니었다고 인정되는 경우에는 설사 그 징계처분이 사후에 사법절차에서 정당한 사유가 없는 것으로 인정되어 무효로 되었다 하더라도 사용자에게 근로기준법 제27조 제1항을 위반하여 정당한 이유 없이 근로자에 대하여 해고 등의 불이익처분을 한다는 인식 즉 고의를 인정할 수 없다.",
      "summ_pass": "어떤 징계사유가 존재하고 당시 사정으로 보아 사용자가 당해 징계처분을 할 만한 정당한 이유가 있다고 판단한 것이 무리가 아니었다고 인정되는 경우에는 설사 그 징계처분이 사후에 사법절차에서 정당한 사유가 없는 것으로 인정되어 무효로 되었다 하더라도 사용자에게 근로기준법 제27조 제1항을 위반하여 정당한 이유 없이 근로자에 대하여 해고 등의 불이익처분을 한다는 인식 즉 고의를 인정할 수 없다."
    }
  ],
  "keyword_tagg": [
    {
      "id": 1,
      "keyword": "정당한 이유"
    },
    {
      "id": 2,
      "keyword": "정당한 사유"
    }
  ],
  "Reference_info": {
    "reference_rules": "근로기준법 제107조, 제27조 제1항 / 형법 제13조",
    "reference_court_case": "가. 대법원 1965. 6. 29. 선고 65도1 판결, 대법원 1965. 7. 6. 선고 65도347 판결 나. 대법원 1974. 11. 12. 선고 74도2676 판결(공1975,8221), 대법원 1983. 2. 22. 선고 82도1636 판결(공1983,617), 대법원 1992. 10. 13. 선고 92도1046 판결(공1992,3185)"
  },
  "Class_info": {
    "class_name": "근로자",
    "instance_name": "근로기준법위반"
  }
}